elasticsearch_helper/__init__.py
elasticsearch_helper/bulk_helper.py
elasticsearch_helper/cmd.py
elasticsearch_helper/index_helper.py
elasticsearch_helper-0.1.2.dist-info/DESCRIPTION.rst
elasticsearch_helper-0.1.2.dist-info/METADATA
elasticsearch_helper-0.1.2.dist-info/RECORD
elasticsearch_helper-0.1.2.dist-info/WHEEL
elasticsearch_helper-0.1.2.dist-info/entry_points.txt
elasticsearch_helper-0.1.2.dist-info/metadata.json
elasticsearch_helper-0.1.2.dist-info/top_level.txt
