Metadata-Version: 2.0
Name: elasticsearch-helper
Version: 0.1.2
Summary: UNKNOWN
Home-page: http://github.com/yuuichi-fujioka/elasticsearch_helper.git
Author: Yuuichi Fujioka
Author-email: fujioka.yuuichi@gmail.com
License: UNKNOWN
Platform: UNKNOWN
Classifier: Intended Audience :: Information Technology
Classifier: Intended Audience :: System Administrators
Classifier: License :: OSI Approved :: Apache Software License
Classifier: Operating System :: POSIX :: Linux
Classifier: Programming Language :: Python
Classifier: Programming Language :: Python :: 2
Classifier: Programming Language :: Python :: 2.7
Requires-Dist: python-dateutil
Requires-Dist: elasticsearch
